pygifconvt_cch/__init__.py
pygifconvt_cch/image_trans_2.py
pygifconvt_cch-1.0.0.dist-info/LICENSE
pygifconvt_cch-1.0.0.dist-info/METADATA
pygifconvt_cch-1.0.0.dist-info/WHEEL
pygifconvt_cch-1.0.0.dist-info/top_level.txt
pygifconvt_cch-1.0.0.dist-info/RECORD
